Q260.v
module fun(a, b, c, d, e);
input a,b,c;
output d,e;
wire w1, w2, w3;

or O1(w1, a, b);
and A1(w2, b, c);
not N1(w3, w1);

or O2(d, w3, w2);
xor X1(e, w2, c);
endmodule




module fun_tb;
reg a,b,c;
wire d,e;
fun a1(a,b,c,d,e);

initial
begin
$dumpfile("check.vcd");
$dumpvars(0,fun_tb);
a=0;b=0;c=0;
#5 a=0;b=0;c=1;
#5 a=0;b=1;c=0;
#5 a=0;b=1;c=1;
#5 a=1;b=0;c=0;
#5 a=1;b=0;c=1;
#5 a=1;b=1;c=0;
#5 a=1;b=1;c=1;
#5 ;

end
endmodule

check.vcd
$date
	Sun Oct 24 13:38:24 2021
$end
$version
	Icarus Verilog
$end
$timescale
	1s
$end
$scope module fun_tb $end
$var wire 1 ! e $end
$var wire 1 " d $end
$var reg 1 # a $end
$var reg 1 $ b $end
$var reg 1 % c $end
$scope module a1 $end
$var wire 1 # a $end
$var wire 1 $ b $end
$var wire 1 % c $end
$var wire 1 " d $end
$var wire 1 ! e $end
$var wire 1 & w1 $end
$var wire 1 ' w2 $end
$var wire 1 ( w3 $end
$upscope $end
$upscope $end
$enddefinitions $end
#0
$dumpvars
1(
0'
0&
0%
0$
0#
1"
0!
$end
#5
1!
1%
#10
0"
0(
0!
1&
0%
1$
#15
1"
1'
0!
1%
#20
0"
0'
0%
0$
1#
#25
1!
1%
#30
0!
0%
1$
#35
1"
1'
0!
1%
